MANIFEST.in
setup.py
src/pants/__init__.py
src/pants/contrib/__init__.py
src/pants/contrib/spindle/__init__.py
src/pants/contrib/spindle/register.py
src/pants/contrib/spindle/targets/__init__.py
src/pants/contrib/spindle/targets/spindle_thrift_library.py
src/pants/contrib/spindle/tasks/__init__.py
src/pants/contrib/spindle/tasks/spindle_gen.py
src/pantsbuild.pants.contrib.spindle.egg-info/PKG-INFO
src/pantsbuild.pants.contrib.spindle.egg-info/SOURCES.txt
src/pantsbuild.pants.contrib.spindle.egg-info/dependency_links.txt
src/pantsbuild.pants.contrib.spindle.egg-info/entry_points.txt
src/pantsbuild.pants.contrib.spindle.egg-info/namespace_packages.txt
src/pantsbuild.pants.contrib.spindle.egg-info/pbr.json
src/pantsbuild.pants.contrib.spindle.egg-info/requires.txt
src/pantsbuild.pants.contrib.spindle.egg-info/top_level.txt
src/pantsbuild.pants.contrib.spindle.egg-info/zip-safe