Metadata-Version: 1.1
Name: pantsbuild.pants.contrib.spindle
Version: 0.0.50
Summary: Spindle thrift -> scala generator pants plugins.
Home-page: https://github.com/pantsbuild/pants
Author: UNKNOWN
Author-email: UNKNOWN
License: Apache License, Version 2.0
Platform: UNKNOWN
Classifier: Intended Audience :: Developers
Classifier: License :: OSI Approved :: Apache Software License
Classifier: Operating System :: MacOS :: MacOS X
Classifier: Operating System :: POSIX :: Linux
Classifier: Programming Language :: Python
Classifier: Topic :: Software Development :: Build Tools
Classifier: Topic :: Software Development :: Code Generators
